LICENSE
README.md
pyproject.toml
setup.py
accumulation_tree/__init__.py
accumulation_tree/abctree.py
accumulation_tree/accumulation_tree.pyx
accumulation_tree/treeslice.py
accumulation_tree.egg-info/PKG-INFO
accumulation_tree.egg-info/SOURCES.txt
accumulation_tree.egg-info/dependency_links.txt
accumulation_tree.egg-info/top_level.txt