Metadata-Version: 2.1
Name: accumulation_tree
Version: 0.6.4
Summary: Red/black tree with support for fast accumulation of values in a key range
Author-email: Timo Kluck <tkluck@infty.nl>
License: MIT License
Project-URL: Homepage, https://github.com/tkluck/accumulation_tree
Keywords: BST,data structure,accumulation
Classifier: Development Status :: 5 - Production/Stable
Classifier: License :: OSI Approved :: MIT License
Classifier: Programming Language :: Python
Classifier: Topic :: Scientific/Engineering
Classifier: Programming Language :: Python :: 2
Classifier: Programming Language :: Python :: 3
License-File: LICENSE
